CHANGES.rst
MANIFEST.in
README.rst
setup.py
collective/__init__.py
collective.venue.egg-info/PKG-INFO
collective.venue.egg-info/SOURCES.txt
collective.venue.egg-info/dependency_links.txt
collective.venue.egg-info/entry_points.txt
collective.venue.egg-info/namespace_packages.txt
collective.venue.egg-info/not-zip-safe
collective.venue.egg-info/requires.txt
collective.venue.egg-info/top_level.txt
collective/venue/__init__.py
collective/venue/behaviors.py
collective/venue/configure.zcml
collective/venue/eventaccessor.py
collective/venue/geolocation.py
collective/venue/icalexporter.py
collective/venue/indexer.py
collective/venue/interfaces.py
collective/venue/setuphandlers.py
collective/venue/upgrades.py
collective/venue/utils.py
collective/venue/browser/__init__.py
collective/venue/browser/configure.zcml
collective/venue/browser/controlpanel.py
collective/venue/browser/event_summary.pt
collective/venue/browser/locationsearch.py
collective/venue/browser/portlet_events.pt
collective/venue/browser/venue.pt
collective/venue/browser/venue.py
collective/venue/browser/venue_base.pt
collective/venue/browser/venue_overlay.pt
collective/venue/browser/venuetile.py
collective/venue/locales/collective.venue.pot
collective/venue/locales/merge-plone.pot
collective/venue/locales/plone.pot
collective/venue/locales/rebuild_i18n.sh
collective/venue/locales/de/LC_MESSAGES/collective.venue.po
collective/venue/locales/de/LC_MESSAGES/plone.po
collective/venue/locales/it/LC_MESSAGES/collective.venue.po
collective/venue/locales/it/LC_MESSAGES/plone.po
collective/venue/profiles/base/browserlayer.xml
collective/venue/profiles/base/controlpanel.xml
collective/venue/profiles/base/metadata.xml
collective/venue/profiles/base/registry.xml
collective/venue/profiles/base/types.xml
collective/venue/profiles/base/types/Event.xml
collective/venue/profiles/base/types/Venue.xml
collective/venue/profiles/default-geolocation/metadata.xml
collective/venue/profiles/default-nogeolocation/metadata.xml
collective/venue/profiles/geolocation_to_2/registry.xml
collective/venue/profiles/uninstall/browserlayer.xml
collective/venue/profiles/uninstall/controlpanel.xml
collective/venue/profiles/uninstall/registry.xml
collective/venue/profiles/uninstall/types.xml
collective/venue/profiles/uninstall/types/Event.xml
