Metadata-Version: 2.1
Name: collective.venue
Version: 4.0
Summary: Dexterity venue type for use with events.
Home-page: https://github.com/collective/collective.venue
Author: Johannes Raggam
Author-email: raggam-nl@adm.at
License: GPL
Keywords: plone collective event geo location
Platform: UNKNOWN
Classifier: Framework :: Plone
Classifier: Framework :: Plone :: 5.1
Classifier: Framework :: Plone :: 5.2
Classifier: Programming Language :: Python
Classifier: Programming Language :: Python :: 2.7
Classifier: Programming Language :: Python :: 3.6
Classifier: Programming Language :: Python :: 3.7
Classifier: Topic :: Software Development :: Libraries :: Python Modules
Provides-Extra: geolocation
